odoo/addons/product_supplierinfo_code/README.rst
odoo/addons/product_supplierinfo_code/__init__.py
odoo/addons/product_supplierinfo_code/__manifest__.py
odoo/addons/product_supplierinfo_code/i18n/es.po
odoo/addons/product_supplierinfo_code/i18n/it.po
odoo/addons/product_supplierinfo_code/i18n/product_supplierinfo_code.pot
odoo/addons/product_supplierinfo_code/models/__init__.py
odoo/addons/product_supplierinfo_code/models/product_template.py
odoo/addons/product_supplierinfo_code/readme/CONTRIBUTORS.md
odoo/addons/product_supplierinfo_code/readme/DESCRIPTION.md
odoo/addons/product_supplierinfo_code/static/description/icon.png
odoo/addons/product_supplierinfo_code/static/description/index.html
odoo/addons/product_supplierinfo_code/tests/__init__.py
odoo/addons/product_supplierinfo_code/tests/test_supplierinfo_code.py
odoo/addons/product_supplierinfo_code/views/product_template.xml
odoo_addon_product_supplierinfo_code-17.0.1.0.0.2.dist-info/METADATA
odoo_addon_product_supplierinfo_code-17.0.1.0.0.2.dist-info/WHEEL
odoo_addon_product_supplierinfo_code-17.0.1.0.0.2.dist-info/top_level.txt
odoo_addon_product_supplierinfo_code-17.0.1.0.0.2.dist-info/RECORD
